{"v":"5.4.3","fr":29.9700012207031,"ip":0,"op":59.0000024031193,"w":1920,"h":1080,"nm":"Background/MarvAndLucy","ddd":0,"assets":[],"layers":[{"ddd":0,"ind":1,"ty":4,"nm":"Bow/MarvAndLucy Outlines","sr":1,"ks":{"o":{"a":0,"k":100,"ix":11},"r":{"a":0,"k":0.42,"ix":10},"p":{"a":1,"k":[{"i":{"x":0.833,"y":0.833},"o":{"x":0.167,"y":0.167},"n":"0p833_0p833_0p167_0p167","t":-20,"s":[902,432,0],"e":[824,350,0],"to":[0,-1.86538851261139,0],"ti":[-1.21981429401785e-8,2.35697746276855,0]},{"i":{"x":0.57,"y":0.447},"o":{"x":0.167,"y":0.167},"n":"0p57_0p447_0p167_0p167","t":0,"s":[824,350,0],"e":[806.343,328.665,0],"to":[3.71528585674241e-10,-0.07176414877176,0],"ti":[-20.9377899169922,-20.1519870758057,0]},{"i":{"x":0.704,"y":1},"o":{"x":0.328,"y":0.199},"n":"0p704_1_0p328_0p199","t":12,"s":[806.343,328.665,0],"e":[906,428.849,0],"to":[20.0426483154297,19.2904396057129,0],"ti":[-2.3298980522668e-9,-1.52612642523309e-8,0]},{"i":{"x":0.661,"y":0.795},"o":{"x":0.297,"y":0},"n":"0p661_0p795_0p297_0","t":30,"s":[906,428.849,0],"e":[831.833,338.241,0],"to":[9.20056208997266e-9,6.0266870605119e-8,0],"ti":[17.256965637207,16.4170989990234,0]},{"i":{"x":0.833,"y":0.833},"o":{"x":0.426,"y":0.812},"n":"0p833_0p833_0p426_0p812","t":45,"s":[831.833,338.241,0],"e":[822,349,0],"to":[-23.7028732299805,-22.549295425415,0],"ti":[-6.80597622704227e-9,-0.0569647103548,0]},{"i":{"x":0.833,"y":0.833},"o":{"x":0.167,"y":0.167},"n":"0p833_0p833_0p167_0p167","t":59,"s":[822,349,0],"e":[902,432,0],"to":[3.21614919585045e-7,2.69178915023804,0],"ti":[-1.17611307359766e-8,-0.09843807667494,0]},{"t":79.000003217736}],"ix":2},"a":{"a":0,"k":[126.5,148.5,0],"ix":1},"s":{"a":1,"k":[{"i":{"x":[0.581,0.581,0.667],"y":[1.019,1.019,1]},"o":{"x":[0.351,0.351,0.333],"y":[-1.083,-1.056,0]},"n":["0p581_1p019_0p351_-1p083","0p581_1p019_0p351_-1p056","0p667_1_0p333_0"],"t":5,"s":[98.771,101.332,100],"e":[0,0,100]},{"i":{"x":[0.423,0.423,0.667],"y":[1.773,1.754,1]},"o":{"x":[0.566,0.566,0.333],"y":[0.034,0.033,0]},"n":["0p423_1p773_0p566_0p034","0p423_1p754_0p566_0p033","0p667_1_0p333_0"],"t":35,"s":[0,0,100],"e":[98.771,101.332,100]},{"t":59.0000024031193}],"ix":6}},"ao":0,"shapes":[{"ty":"gr","it":[{"ind":0,"ty":"sh","ix":1,"ks":{"a":0,"k":{"i":[[16.67,-15.322],[-17.573,-19],[-17.193,25.311],[23.435,14.587]],"o":[[-20.012,18.393],[21.082,22.794],[15.126,-22.268],[-18.236,-11.351]],"v":[[-36.035,-38.244],[-38.561,31.803],[41.008,26.799],[24.589,-43.247]],"c":true},"ix":2},"nm":"Path 1","mn":"ADBE Vector Shape - Group","hd":false},{"ty":"fl","c":{"a":0,"k":[0.481999984442,0.275,0.560999971278,1],"ix":4},"o":{"a":0,"k":100,"ix":5},"r":1,"bm":0,"nm":"Fill 1","mn":"ADBE Vector Graphic - Fill","hd":false},{"ty":"tr","p":{"a":0,"k":[124.181,160.656],"ix":2},"a":{"a":0,"k":[0,0],"ix":1},"s":{"a":0,"k":[100,100],"ix":3},"r":{"a":0,"k":0,"ix":6},"o":{"a":0,"k":100,"ix":7},"sk":{"a":0,"k":0,"ix":4},"sa":{"a":0,"k":0,"ix":5},"nm":"Transform"}],"nm":"Group 1","np":2,"cix":2,"bm":0,"ix":1,"mn":"ADBE Vector Group","hd":false},{"ty":"gr","it":[{"ind":0,"ty":"sh","ix":1,"ks":{"a":0,"k":{"i":[[32.563,38.518],[14.334,-21.462],[0,-0.001],[-2.424,-2.708],[-9.226,-11.399],[-8.898,-19.668],[-4.444,-3.458],[-1.653,0.578]],"o":[[-33.962,-40.173],[-6.287,9.414],[-0.036,12.191],[11.686,13.05],[5.995,7.405],[4.615,10.204],[12.916,10.051],[33.591,-11.742]],"v":[[49.413,-44.354],[-75.624,-35.597],[-81.939,-16.834],[-71.835,6.931],[-41.523,25.693],[-30.155,55.712],[-18.79,74.475],[16.574,76.978]],"c":true},"ix":2},"nm":"Path 1","mn":"ADBE Vector Shape - Group","hd":false},{"ty":"fl","c":{"a":0,"k":[0.717999985639,0.510000011968,0.795999983245,1],"ix":4},"o":{"a":0,"k":100,"ix":5},"r":1,"bm":0,"nm":"Fill 1","mn":"ADBE Vector Graphic - Fill","hd":false},{"ty":"tr","p":{"a":0,"k":[82.225,211.596],"ix":2},"a":{"a":0,"k":[0,0],"ix":1},"s":{"a":0,"k":[100,100],"ix":3},"r":{"a":0,"k":0,"ix":6},"o":{"a":0,"k":100,"ix":7},"sk":{"a":0,"k":0,"ix":4},"sa":{"a":0,"k":0,"ix":5},"nm":"Transform"}],"nm":"Group 2","np":2,"cix":2,"bm":0,"ix":2,"mn":"ADBE Vector Group","hd":false},{"ty":"gr","it":[{"ind":0,"ty":"sh","ix":1,"ks":{"a":0,"k":{"i":[[3.473,1.267],[6.14,-2.227],[-18.16,-39.181],[-24.723,-2.722],[-3.69,33.545],[9.385,10.759],[2.661,0.268],[9.108,5.825],[11.593,12.308]],"o":[[-4.511,-0.143],[-30.99,11.246],[11.171,24.1],[48.514,5.339],[0.629,-5.719],[-8.454,-9.691],[-23.083,-2.326],[-7.832,-5.01],[-4.038,-4.287]],"v":[[-16.452,-75.772],[-32.871,-73.271],[-68.235,28.047],[-7.611,70.576],[84.145,-3.279],[77.01,-34.495],[53.013,-45.752],[8.272,-35.531],[-4.237,-67.946]],"c":true},"ix":2},"nm":"Path 1","mn":"ADBE Vector Shape - Group","hd":false},{"ty":"fl","c":{"a":0,"k":[0.717999985639,0.510000011968,0.795999983245,1],"ix":4},"o":{"a":0,"k":100,"ix":5},"r":1,"bm":0,"nm":"Fill 1","mn":"ADBE Vector Graphic - Fill","hd":false},{"ty":"tr","p":{"a":0,"k":[165.627,76.165],"ix":2},"a":{"a":0,"k":[0,0],"ix":1},"s":{"a":0,"k":[100,100],"ix":3},"r":{"a":0,"k":0,"ix":6},"o":{"a":0,"k":100,"ix":7},"sk":{"a":0,"k":0,"ix":4},"sa":{"a":0,"k":0,"ix":5},"nm":"Transform"}],"nm":"Group 3","np":2,"cix":2,"bm":0,"ix":3,"mn":"ADBE Vector Group","hd":false}],"ip":0,"op":59.9400024414062,"st":0,"bm":0},{"ddd":0,"ind":2,"ty":4,"nm":"pupils/MarvAndLucy Outlines","parent":3,"sr":1,"ks":{"o":{"a":0,"k":100,"ix":11},"r":{"a":0,"k":0,"ix":10},"p":{"a":0,"k":[188.5,72.5,0],"ix":2},"a":{"a":0,"k":[130,38,0],"ix":1},"s":{"a":0,"k":[100,100,100],"ix":6}},"ao":0,"shapes":[{"ty":"gr","it":[{"ind":0,"ty":"sh","ix":1,"ks":{"a":0,"k":{"i":[[0,-5.382],[5.435,0],[0,5.382],[-5.434,0]],"o":[[0,5.382],[-5.434,0],[0,-5.382],[5.435,0]],"v":[[9.84,-0.001],[-0.001,9.746],[-9.84,-0.001],[-0.001,-9.746]],"c":true},"ix":2},"nm":"Path 1","mn":"ADBE Vector Shape - Group","hd":false},{"ty":"fl","c":{"a":0,"k":[1,1,1,1],"ix":4},"o":{"a":0,"k":100,"ix":5},"r":1,"bm":0,"nm":"Fill 1","mn":"ADBE Vector Graphic - Fill","hd":false},{"ty":"tr","p":{"a":0,"k":[245.361,17.459],"ix":2},"a":{"a":0,"k":[0,0],"ix":1},"s":{"a":0,"k":[100,100],"ix":3},"r":{"a":0,"k":0,"ix":6},"o":{"a":0,"k":100,"ix":7},"sk":{"a":0,"k":0,"ix":4},"sa":{"a":0,"k":0,"ix":5},"nm":"Transform"}],"nm":"Group 1","np":2,"cix":2,"bm":0,"ix":1,"mn":"ADBE Vector Group","hd":false},{"ty":"gr","it":[{"ind":0,"ty":"sh","ix":1,"ks":{"a":0,"k":{"i":[[0,-5.382],[5.435,0],[0,5.382],[-5.434,0]],"o":[[0,5.382],[-5.434,0],[0,-5.382],[5.435,0]],"v":[[9.84,0],[-0.001,9.745],[-9.84,0],[-0.001,-9.745]],"c":true},"ix":2},"nm":"Path 1","mn":"ADBE Vector Shape - Group","hd":false},{"ty":"fl","c":{"a":0,"k":[1,1,1,1],"ix":4},"o":{"a":0,"k":100,"ix":5},"r":1,"bm":0,"nm":"Fill 1","mn":"ADBE Vector Graphic - Fill","hd":false},{"ty":"tr","p":{"a":0,"k":[225.68,30.842],"ix":2},"a":{"a":0,"k":[0,0],"ix":1},"s":{"a":0,"k":[100,100],"ix":3},"r":{"a":0,"k":0,"ix":6},"o":{"a":0,"k":100,"ix":7},"sk":{"a":0,"k":0,"ix":4},"sa":{"a":0,"k":0,"ix":5},"nm":"Transform"}],"nm":"Group 2","np":2,"cix":2,"bm":0,"ix":2,"mn":"ADBE Vector Group","hd":false},{"ty":"gr","it":[{"ind":0,"ty":"sh","ix":1,"ks":{"a":0,"k":{"i":[[0,-13.611],[13.743,0],[0,13.612],[-13.744,0]],"o":[[0,13.612],[-13.744,0],[0,-13.611],[13.743,0]],"v":[[24.886,0],[0.001,24.646],[-24.886,0],[0.001,-24.646]],"c":true},"ix":2},"nm":"Path 1","mn":"ADBE Vector Shape - Group","hd":false},{"ty":"fl","c":{"a":0,"k":[0.144999994016,0.144999994016,0.144999994016,1],"ix":4},"o":{"a":0,"k":100,"ix":5},"r":1,"bm":0,"nm":"Fill 1","mn":"ADBE Vector Graphic - Fill","hd":false},{"ty":"tr","p":{"a":0,"k":[234.027,24.896],"ix":2},"a":{"a":0,"k":[0,0],"ix":1},"s":{"a":0,"k":[100,100],"ix":3},"r":{"a":0,"k":0,"ix":6},"o":{"a":0,"k":100,"ix":7},"sk":{"a":0,"k":0,"ix":4},"sa":{"a":0,"k":0,"ix":5},"nm":"Transform"}],"nm":"Group 3","np":2,"cix":2,"bm":0,"ix":3,"mn":"ADBE Vector Group","hd":false},{"ty":"gr","it":[{"ind":0,"ty":"sh","ix":1,"ks":{"a":0,"k":{"i":[[0,-5.382],[5.434,0],[0,5.382],[-5.435,0]],"o":[[0,5.382],[-5.435,0],[0,-5.382],[5.434,0]],"v":[[9.84,0],[0,9.746],[-9.84,0],[0,-9.746]],"c":true},"ix":2},"nm":"Path 1","mn":"ADBE Vector Shape - Group","hd":false},{"ty":"fl","c":{"a":0,"k":[1,1,1,1],"ix":4},"o":{"a":0,"k":100,"ix":5},"r":1,"bm":0,"nm":"Fill 1","mn":"ADBE Vector Graphic - Fill","hd":false},{"ty":"tr","p":{"a":0,"k":[19.775,56.33],"ix":2},"a":{"a":0,"k":[0,0],"ix":1},"s":{"a":0,"k":[100,100],"ix":3},"r":{"a":0,"k":0,"ix":6},"o":{"a":0,"k":100,"ix":7},"sk":{"a":0,"k":0,"ix":4},"sa":{"a":0,"k":0,"ix":5},"nm":"Transform"}],"nm":"Group 4","np":2,"cix":2,"bm":0,"ix":4,"mn":"ADBE Vector Group","hd":false},{"ty":"gr","it":[{"ind":0,"ty":"sh","ix":1,"ks":{"a":0,"k":{"i":[[0,-5.382],[5.435,0],[0,5.382],[-5.434,0]],"o":[[0,5.382],[-5.434,0],[0,-5.382],[5.435,0]],"v":[[9.84,-0.001],[-0.001,9.745],[-9.84,-0.001],[-0.001,-9.745]],"c":true},"ix":2},"nm":"Path 1","mn":"ADBE Vector Shape - Group","hd":false},{"ty":"fl","c":{"a":0,"k":[1,1,1,1],"ix":4},"o":{"a":0,"k":100,"ix":5},"r":1,"bm":0,"nm":"Fill 1","mn":"ADBE Vector Graphic - Fill","hd":false},{"ty":"tr","p":{"a":0,"k":[39.456,40.588],"ix":2},"a":{"a":0,"k":[0,0],"ix":1},"s":{"a":0,"k":[100,100],"ix":3},"r":{"a":0,"k":0,"ix":6},"o":{"a":0,"k":100,"ix":7},"sk":{"a":0,"k":0,"ix":4},"sa":{"a":0,"k":0,"ix":5},"nm":"Transform"}],"nm":"Group 5","np":2,"cix":2,"bm":0,"ix":5,"mn":"ADBE Vector Group","hd":false},{"ty":"gr","it":[{"ind":0,"ty":"sh","ix":1,"ks":{"a":0,"k":{"i":[[0,-14.428],[14.568,0],[0,14.428],[-14.569,0]],"o":[[0,14.428],[-14.569,0],[0,-14.428],[14.568,0]],"v":[[26.379,0],[0,26.125],[-26.379,0],[0,-26.125]],"c":true},"ix":2},"nm":"Path 1","mn":"ADBE Vector Shape - Group","hd":false},{"ty":"fl","c":{"a":0,"k":[0.144999994016,0.144999994016,0.144999994016,1],"ix":4},"o":{"a":0,"k":100,"ix":5},"r":1,"bm":0,"nm":"Fill 1","mn":"ADBE Vector Graphic - Fill","hd":false},{"ty":"tr","p":{"a":0,"k":[26.629,49.542],"ix":2},"a":{"a":0,"k":[0,0],"ix":1},"s":{"a":0,"k":[100,100],"ix":3},"r":{"a":0,"k":0,"ix":6},"o":{"a":0,"k":100,"ix":7},"sk":{"a":0,"k":0,"ix":4},"sa":{"a":0,"k":0,"ix":5},"nm":"Transform"}],"nm":"Group 6","np":2,"cix":2,"bm":0,"ix":6,"mn":"ADBE Vector Group","hd":false}],"ip":0,"op":59.9400024414062,"st":0,"bm":0},{"ddd":0,"ind":3,"ty":4,"nm":"Eyes/MarvAndLucy Outlines","parent":5,"sr":1,"ks":{"o":{"a":0,"k":100,"ix":11},"r":{"a":0,"k":0,"ix":10},"p":{"a":1,"k":[{"i":{"x":0.833,"y":0.833},"o":{"x":0.167,"y":0.167},"n":"0p833_0p833_0p167_0p167","t":0,"s":[290.774,134.314,0],"e":[283.703,130.367,0],"to":[-1.17855477333069,-0.65790361166,0],"ti":[0,0.0822379514575,0]},{"i":{"x":0.833,"y":0.833},"o":{"x":0.167,"y":0.167},"n":"0p833_0p833_0p167_0p167","t":30,"s":[283.703,130.367,0],"e":[290.774,133.821,0],"to":[0,-0.0822379514575,0],"ti":[-1.17855477333069,-0.57566565275192,0]},{"t":59.0000024031193}],"ix":2},"a":{"a":0,"k":[176.5,92.5,0],"ix":1},"s":{"a":0,"k":[101.019,98.686,100],"ix":6}},"ao":0,"shapes":[{"ty":"gr","it":[{"ind":0,"ty":"sh","ix":1,"ks":{"a":0,"k":{"i":[[0,-43.917],[42.392,0],[0,43.917],[-42.392,0]],"o":[[0,43.917],[-42.392,0],[0,-43.917],[42.392,0]],"v":[[76.758,0],[0,79.519],[-76.758,0],[0,-79.519]],"c":true},"ix":2},"nm":"Path 1","mn":"ADBE Vector Shape - Group","hd":false},{"ty":"fl","c":{"a":0,"k":[1,1,1,1],"ix":4},"o":{"a":0,"k":100,"ix":5},"r":1,"bm":0,"nm":"Fill 1","mn":"ADBE Vector Graphic - Fill","hd":false},{"ty":"tr","p":{"a":0,"k":[77.008,104.786],"ix":2},"a":{"a":0,"k":[0,0],"ix":1},"s":{"a":0,"k":[100,100],"ix":3},"r":{"a":0,"k":0,"ix":6},"o":{"a":0,"k":100,"ix":7},"sk":{"a":0,"k":0,"ix":4},"sa":{"a":0,"k":0,"ix":5},"nm":"Transform"}],"nm":"Group 1","np":2,"cix":2,"bm":0,"ix":1,"mn":"ADBE Vector Group","hd":false},{"ty":"gr","it":[{"ind":0,"ty":"sh","ix":1,"ks":{"a":0,"k":{"i":[[0,-43.917],[42.393,0],[0,43.917],[-42.391,0]],"o":[[0,43.917],[-42.391,0],[0,-43.917],[42.393,0]],"v":[[76.759,0],[0,79.519],[-76.758,0],[0,-79.519]],"c":true},"ix":2},"nm":"Path 1","mn":"ADBE Vector Shape - Group","hd":false},{"ty":"fl","c":{"a":0,"k":[1,1,1,1],"ix":4},"o":{"a":0,"k":100,"ix":5},"r":1,"bm":0,"nm":"Fill 1","mn":"ADBE Vector Graphic - Fill","hd":false},{"ty":"tr","p":{"a":0,"k":[275.341,79.769],"ix":2},"a":{"a":0,"k":[0,0],"ix":1},"s":{"a":0,"k":[100,100],"ix":3},"r":{"a":0,"k":0,"ix":6},"o":{"a":0,"k":100,"ix":7},"sk":{"a":0,"k":0,"ix":4},"sa":{"a":0,"k":0,"ix":5},"nm":"Transform"}],"nm":"Group 2","np":2,"cix":2,"bm":0,"ix":2,"mn":"ADBE Vector Group","hd":false}],"ip":0,"op":59.9400024414062,"st":0,"bm":0},{"ddd":0,"ind":4,"ty":4,"nm":"Open/MarvAndLucy Outlines","parent":5,"sr":1,"ks":{"o":{"a":0,"k":100,"ix":11},"r":{"a":0,"k":0,"ix":10},"p":{"a":0,"k":[263.499,260.632,0],"ix":2},"a":{"a":0,"k":[75,47.5,0],"ix":1},"s":{"a":0,"k":[101.019,98.686,100],"ix":6}},"ao":0,"shapes":[{"ty":"gr","it":[{"ind":0,"ty":"sh","ix":1,"ks":{"a":0,"k":{"i":[[-0.019,0.061],[-22.02,-1.44],[0.011,0.07],[21.372,2.912]],"o":[[0.021,-0.068],[18.163,1.188],[-0.012,-0.078],[-18.645,-2.541]],"v":[[-34.728,-7.037],[3.161,4.868],[34.737,0.403],[-3.375,4.192]],"c":true},"ix":2},"nm":"Path 1","mn":"ADBE Vector Shape - Group","hd":false},{"ty":"st","c":{"a":0,"k":[0.969999964097,0.969999964097,0.969999964097,1],"ix":3},"o":{"a":0,"k":100,"ix":4},"w":{"a":0,"k":16,"ix":5},"lc":1,"lj":1,"ml":10,"ml2":{"a":0,"k":10,"ix":8},"bm":0,"nm":"Stroke 1","mn":"ADBE Vector Graphic - Stroke","hd":false},{"ty":"fl","c":{"a":0,"k":[1,1,1,1],"ix":4},"o":{"a":0,"k":100,"ix":5},"r":1,"bm":0,"nm":"Fill 1","mn":"ADBE Vector Graphic - Fill","hd":false},{"ty":"tr","p":{"a":0,"k":[74.747,47.105],"ix":2},"a":{"a":0,"k":[0,0],"ix":1},"s":{"a":0,"k":[100,100],"ix":3},"r":{"a":0,"k":0,"ix":6},"o":{"a":0,"k":100,"ix":7},"sk":{"a":0,"k":0,"ix":4},"sa":{"a":0,"k":0,"ix":5},"nm":"Transform"}],"nm":"Group 1","np":3,"cix":2,"bm":0,"ix":1,"mn":"ADBE Vector Group","hd":false}],"ip":0,"op":59.9400024414062,"st":0,"bm":0},{"ddd":0,"ind":5,"ty":4,"nm":"Body/MarvAndLucy Outlines","sr":1,"ks":{"o":{"a":0,"k":100,"ix":11},"r":{"a":0,"k":0,"ix":10},"p":{"a":0,"k":[960,552,0],"ix":2},"a":{"a":0,"k":[214,233,0],"ix":1},"s":{"a":1,"k":[{"i":{"x":[0.581,0.581,0.667],"y":[1.019,1.019,1]},"o":{"x":[0.351,0.351,0.333],"y":[-1.083,-1.056,0]},"n":["0p581_1p019_0p351_-1p083","0p581_1p019_0p351_-1p056","0p667_1_0p333_0"],"t":0,"s":[98.771,101.332,100],"e":[0,0,100]},{"i":{"x":[0.423,0.423,0.667],"y":[1.935,1.911,1]},"o":{"x":[0.566,0.566,0.333],"y":[0.041,0.04,0]},"n":["0p423_1p935_0p566_0p041","0p423_1p911_0p566_0p04","0p667_1_0p333_0"],"t":30,"s":[0,0,100],"e":[98.771,101.332,100]},{"t":59.0000024031193}],"ix":6}},"ao":0,"shapes":[{"ty":"gr","it":[{"ind":0,"ty":"sh","ix":1,"ks":{"a":0,"k":{"i":[[-3.747,-0.019],[-36.291,-15.746],[1.619,-88],[25.143,-35.096],[74.018,98.955],[-17.479,42.815],[-63.627,22.908]],"o":[[0,0],[79.758,34.608],[-0.67,36.457],[-66.964,93.468],[-58.177,-77.778],[12.523,-30.675],[27.706,-9.976]],"v":[[17.544,-232.716],[94.688,-216.767],[212.045,16.201],[185.523,126.273],[-155.487,133.779],[-150.435,-98.876],[-45.606,-222.708]],"c":true},"ix":2},"nm":"Path 1","mn":"ADBE Vector Shape - Group","hd":false},{"ty":"fl","c":{"a":0,"k":[0.957000014361,0.752999997606,0.941000007181,1],"ix":4},"o":{"a":0,"k":100,"ix":5},"r":1,"bm":0,"nm":"Fill 1","mn":"ADBE Vector Graphic - Fill","hd":false},{"ty":"tr","p":{"a":0,"k":[213.914,232.985],"ix":2},"a":{"a":0,"k":[0,0],"ix":1},"s":{"a":0,"k":[100,100],"ix":3},"r":{"a":0,"k":0,"ix":6},"o":{"a":0,"k":100,"ix":7},"sk":{"a":0,"k":0,"ix":4},"sa":{"a":0,"k":0,"ix":5},"nm":"Transform"}],"nm":"Group 1","np":2,"cix":2,"bm":0,"ix":1,"mn":"ADBE Vector Group","hd":false}],"ip":0,"op":59.9400024414062,"st":0,"bm":0},{"ddd":0,"ind":6,"ty":4,"nm":"Tail/MarvAndLucy Outlines","parent":5,"sr":1,"ks":{"o":{"a":0,"k":100,"ix":11},"r":{"a":0,"k":0,"ix":10},"p":{"a":0,"k":[226.122,398.792,0],"ix":2},"a":{"a":0,"k":[261,141,0],"ix":1},"s":{"a":1,"k":[{"i":{"x":[0.833,0.833,0.833],"y":[0.833,0.833,0.833]},"o":{"x":[0.167,0.167,0.167],"y":[0.167,0.167,0.167]},"n":["0p833_0p833_0p167_0p167","0p833_0p833_0p167_0p167","0p833_0p833_0p167_0p167"],"t":0,"s":[101.019,98.686,100],"e":[101.019,85.844,100]},{"i":{"x":[0.833,0.833,0.833],"y":[0.833,0.833,0.833]},"o":{"x":[0.167,0.167,0.167],"y":[0.167,0.167,0.167]},"n":["0p833_0p833_0p167_0p167","0p833_0p833_0p167_0p167","0p833_0p833_0p167_0p167"],"t":17,"s":[101.019,85.844,100],"e":[101.019,85.844,100]},{"i":{"x":[0.833,0.833,0.833],"y":[0.833,0.833,0.833]},"o":{"x":[0.167,0.167,0.167],"y":[0.167,0.167,0.167]},"n":["0p833_0p833_0p167_0p167","0p833_0p833_0p167_0p167","0p833_0p833_0p167_0p167"],"t":22,"s":[101.019,85.844,100],"e":[101.019,98.686,100]},{"t":59.0000024031193}],"ix":6,"x":"var $bm_rt;\n$bm_rt = transform.scale;"}},"ao":0,"shapes":[{"ty":"gr","it":[{"ind":0,"ty":"sh","ix":1,"ks":{"a":0,"k":{"i":[[9.921,-20.581],[11.915,-2.294],[26.076,-12.309],[42.788,-30.82],[6.22,-0.615],[7.335,3.644],[38.477,5.17],[30.802,-0.741],[12.293,18.641],[-2.507,6.219],[-62.17,-97.238]],"o":[[-8.641,17.931],[-50.995,9.813],[-30.911,14.591],[-19.987,14.399],[-27.935,2.765],[-55.261,-27.462],[-16.466,-2.209],[-13.169,0.315],[-10.16,-15.41],[37.126,-92.199],[5.062,7.917]],"v":[[250.824,11.593],[205.356,36.61],[110.633,29.105],[53.16,120.198],[5.805,137.925],[-51.031,126.669],[-143.228,37.859],[-191.222,46.616],[-250.585,29.105],[-249.32,-14.677],[238.711,-43.452]],"c":true},"ix":2},"nm":"Path 1","mn":"ADBE Vector Shape - Group","hd":false},{"ty":"fl","c":{"a":0,"k":[0.957000014361,0.752999997606,0.941000007181,1],"ix":4},"o":{"a":0,"k":100,"ix":5},"r":1,"bm":0,"nm":"Fill 1","mn":"ADBE Vector Graphic - Fill","hd":false},{"ty":"tr","p":{"a":0,"k":[260.995,140.94],"ix":2},"a":{"a":0,"k":[0,0],"ix":1},"s":{"a":0,"k":[100,100],"ix":3},"r":{"a":0,"k":0,"ix":6},"o":{"a":0,"k":100,"ix":7},"sk":{"a":0,"k":0,"ix":4},"sa":{"a":0,"k":0,"ix":5},"nm":"Transform"}],"nm":"Group 1","np":2,"cix":2,"bm":0,"ix":1,"mn":"ADBE Vector Group","hd":false}],"ip":0,"op":59.9400024414062,"st":0,"bm":0}],"markers":[]}